{
    "id": "OSSA-20250204-1371",
    "version": "1.0.0",
    "severity": "Informational",
    "description": "Javadoc for maven-script-interpreter",
    "title": "Advisory for maven-script-interpreter-javadoc",
    "package_name": "maven-script-interpreter-javadoc",
    "publisher": "Generated by OSSA Collector",
    "last_updated": "2025-02-04T20:27:06.468722",
    "approvals": [
        {
            "consumption": true,
            "externalization": true
        }
    ],
    "purls": [
        "pkg:rpm/amzn/maven-script-interpreter-javadoc@1.2"
    ],
    "regex": [
        "^pkg:rpm/amzn/maven-script-interpreter-javadoc.*"
    ],
    "affected_versions": [
        "*.*",
        "1.2"
    ],
    "artifacts": [],
    "licenses": "ASL 2.0",
    "aliases": [],
    "references": "http://maven.apache.org/shared/maven-script-interpreter/"
}