{
    "id": "OSSA-20250205-5264",
    "version": "1.0.0",
    "severity": "High",
    "description": "Recursive copying of files and directories within Perl 5 toolchain",
    "title": "Advisory for perl-File-Copy-Recursive-Reduced",
    "package_name": "perl-File-Copy-Recursive-Reduced",
    "publisher": "Generated by OSSA Collector",
    "last_updated": "2025-02-05T03:53:42.108373",
    "approvals": [
        {
            "consumption": true,
            "externalization": true
        }
    ],
    "purls": [
        "pkg:rpm/amzn/perl-File-Copy-Recursive-Reduced@0.006"
    ],
    "regex": [
        "^pkg:rpm/amzn/perl-File-Copy-Recursive-Reduced.*"
    ],
    "affected_versions": [
        "*.*",
        "0.006"
    ],
    "artifacts": [
        {
            "url": "file://File-Copy-Recursive-Reduced-0.006.tar.gz",
            "hashes": {
                "sha1": "a169b5b484de39ad37870c2b1e29feaafeb91f2d",
                "sha256": "e618f993a69f4355205c58fffff6982609f28b47f646ec6e244e41b5c6707e2c",
                "ssdeep": "768:nWEnJppr2z0+lwz0x/QIaZ/nEs+vej1E83w:nWUBm0WwzuPa5Ecj1nA",
                "swhid": "swh:1:cnt:a169b5b484de39ad37870c2b1e29feaafeb91f2d"
            },
            "swhid": "swh:1:dir:6a4a706414c8fd3879a07ba7c75cdb177bee0dc3"
        }
    ],
    "licenses": "Artistic, GPL+",
    "aliases": [],
    "references": "https://metacpan.org/release/File-Copy-Recursive-Reduced"
}