{
    "id": "OSSA-20250205-6441",
    "version": "1.0.0",
    "severity": "Medium",
    "description": "Headers for developing programs that will use pangomm2.48",
    "title": "Advisory for pangomm2.48-devel",
    "package_name": "pangomm2.48-devel",
    "publisher": "Generated by OSSA Collector",
    "last_updated": "2025-02-05T02:32:03.366383",
    "approvals": [
        {
            "consumption": true,
            "externalization": true
        }
    ],
    "purls": [
        "pkg:rpm/amzn/pangomm2.48-devel@2.54.0"
    ],
    "regex": [
        "^pkg:rpm/amzn/pangomm2.48-devel.*"
    ],
    "affected_versions": [
        "*.*",
        "2.54.0"
    ],
    "artifacts": [
        {
            "url": "file://pangomm-2.54.0.tar.xz",
            "hashes": {
                "sha1": "e784b2b4ff8ae1b7fc79708c218b8c38f06f6b51",
                "sha256": "4a5b1fd1b7c47a1af45277ea82b5abeaca8e08fb10a27daa6394cf88d74e7acf",
                "ssdeep": "12288:/DfQWPpVv7IkxAHaRlWKiOJ8iIxrVb1CJafPOW7kzjzNkIj/trKIAeUqtlkyc8f:7YWP3uH4WKiqIxFyafm6mn+strKIvlky",
                "swhid": "swh:1:cnt:e784b2b4ff8ae1b7fc79708c218b8c38f06f6b51"
            },
            "swhid": "swh:1:dir:39988013f2d1bf292ca4a307f62cd39b459cd2df"
        }
    ],
    "licenses": "LGPL-2.1-or-later",
    "aliases": [],
    "references": "https://www.gtkmm.org/"
}