{
    "id": "OSSA-20250204-689",
    "version": "1.0.0",
    "severity": "High",
    "description": "The Anthy engine for IBus input platform",
    "title": "Advisory for ibus-anthy",
    "package_name": "ibus-anthy",
    "publisher": "Generated by OSSA Collector",
    "last_updated": "2025-02-04T08:23:16.553536",
    "approvals": [
        {
            "consumption": true,
            "externalization": true
        }
    ],
    "purls": [
        "pkg:rpm/amzn/ibus-anthy@1.5.14"
    ],
    "regex": [
        "^pkg:rpm/amzn/ibus-anthy.*"
    ],
    "affected_versions": [
        "*.*",
        "1.5.14"
    ],
    "artifacts": [
        {
            "url": "file://ibus-anthy-1.5.14.tar.gz",
            "hashes": {
                "sha1": "2cebbeaa8aa9a64d07b9f615723fb4f2737e34c9",
                "sha256": "c8694da18d0b891a48f4d75a0dece37ecbca6d1b1acb64101a7a84cad1046d9b",
                "ssdeep": "12288:GyTRlMtHyCPrPKLDjAMXr28YJkQqhzuNWrDCEeGFd1MiETBkp2hD6uH:GykxDsDjfr2R+QUz3DFd1kB+2hD6i",
                "swhid": "swh:1:cnt:2cebbeaa8aa9a64d07b9f615723fb4f2737e34c9"
            },
            "swhid": "swh:1:dir:434deee08ea2a545c5d07429e949f145d382875a"
        }
    ],
    "licenses": "GPLv2+",
    "aliases": [],
    "references": "https://github.com/ibus/ibus/wiki"
}