{
    "id": "OSSA-20250204-993",
    "version": "1.0.0",
    "severity": "Informational",
    "description": "HTML syntax checker and pretty printer",
    "title": "Advisory for jtidy",
    "package_name": "jtidy",
    "publisher": "Generated by OSSA Collector",
    "last_updated": "2025-02-04T15:01:06.878172",
    "approvals": [
        {
            "consumption": true,
            "externalization": true
        }
    ],
    "purls": [
        "pkg:rpm/amzn/jtidy@1.0"
    ],
    "regex": [
        "^pkg:rpm/amzn/jtidy.*"
    ],
    "affected_versions": [
        "*.*",
        "1.0"
    ],
    "artifacts": [
        {
            "url": "file://jtidy.tar.xz",
            "hashes": {
                "sha1": "30053d4dcf957c4699ce25a9935d93b7a7982255",
                "sha256": "97654df194fda0c4199297bfedda9c0d60c40cb5ab35f80782ca83274dbdd69a",
                "ssdeep": "6144:03rNnehvbo6qGy7QV+TUwnI8e+0s0QOSpZxluXK+LAaNR6:0b10NAlI85GOTluaqm",
                "swhid": "swh:1:cnt:30053d4dcf957c4699ce25a9935d93b7a7982255"
            },
            "swhid": "swh:1:dir:a1b12e8c833e0e4c9b933a9759b3e22f803fa08c"
        }
    ],
    "licenses": "zlib",
    "aliases": [],
    "references": "http://jtidy.sourceforge.net/"
}