{
    "id": "OSSA-20250205-9088",
    "version": "1.0.0",
    "severity": "High",
    "description": "Pack dependencies onto a script file",
    "title": "Advisory for perl-App-FatPacker",
    "package_name": "perl-App-FatPacker",
    "publisher": "Generated by OSSA Collector",
    "last_updated": "2025-02-05T03:40:46.378704",
    "approvals": [
        {
            "consumption": true,
            "externalization": true
        }
    ],
    "purls": [
        "pkg:rpm/amzn/perl-App-FatPacker@0.010008"
    ],
    "regex": [
        "^pkg:rpm/amzn/perl-App-FatPacker.*"
    ],
    "affected_versions": [
        "*.*",
        "0.010008"
    ],
    "artifacts": [
        {
            "url": "file://App-FatPacker-0.010008.tar.gz",
            "hashes": {
                "sha1": "fcb29504c6a0795f633f3773b884eb0c162ed43d",
                "sha256": "129db36dc845661a582286810cfe2d5216eb2ce082bad40ae1fcdce0f45deccf",
                "ssdeep": "192:glSZ/h8rEgLFFw0RVNGGFsBpiK0HV7WYvzkYhW9KTJiAL8ghgLHrDZNh7BKsE79F:8SFh2Ee+0RVNGBpAVT9kYEAL8ghAzZBs",
                "swhid": "swh:1:cnt:fcb29504c6a0795f633f3773b884eb0c162ed43d"
            },
            "swhid": "swh:1:dir:0c8b4592b8b715ea6a6dc31366b0cf43a8c4cc27"
        }
    ],
    "licenses": "Artistic, GPL+",
    "aliases": [],
    "references": "https://metacpan.org/release/App-FatPacker"
}