{
    "id": "OSSA-20250204-651",
    "version": "1.0.0",
    "severity": "High",
    "description": "iSCSI daemon and utility programs",
    "title": "Advisory for iscsi-initiator-utils",
    "package_name": "iscsi-initiator-utils",
    "publisher": "Generated by OSSA Collector",
    "last_updated": "2025-02-04T08:26:09.579099",
    "approvals": [
        {
            "consumption": true,
            "externalization": true
        }
    ],
    "purls": [
        "pkg:rpm/amzn/iscsi-initiator-utils@6.2.1.4"
    ],
    "regex": [
        "^pkg:rpm/amzn/iscsi-initiator-utils.*"
    ],
    "affected_versions": [
        "*.*",
        "6.2.1.4"
    ],
    "artifacts": [
        {
            "url": "file://open-iscsi-2a8f9d8.tar.gz",
            "hashes": {
                "sha1": "548252927c20ea605def18014cbafa377b1b104d",
                "sha256": "c3de3a9b36454ee6e09d23e675f49e44174677a850c446a62939bb433b856e18",
                "ssdeep": "12288:slW/hgBrF5HhrYTkE+dhjkU+2FxJqCqB8h+xC5FuJ4IYW7:sllvBMkddyU+c6GQOFQ4VO",
                "swhid": "swh:1:cnt:548252927c20ea605def18014cbafa377b1b104d"
            },
            "swhid": "swh:1:dir:02d56867c43f923064a8e02741d317356f7b643a"
        }
    ],
    "licenses": "GPLv2+",
    "aliases": [],
    "references": "https://github.com/open-iscsi/open-iscsi"
}