{
    "id": "OSSA-20250205-7908",
    "version": "1.0.0",
    "severity": "Medium",
    "description": "Determine the size of images in several common formats in Perl",
    "title": "Advisory for perl-Image-Size",
    "package_name": "perl-Image-Size",
    "publisher": "Generated by OSSA Collector",
    "last_updated": "2025-02-05T04:00:59.678840",
    "approvals": [
        {
            "consumption": true,
            "externalization": true
        }
    ],
    "purls": [
        "pkg:rpm/amzn/perl-Image-Size@3.300"
    ],
    "regex": [
        "^pkg:rpm/amzn/perl-Image-Size.*"
    ],
    "affected_versions": [
        "*.*",
        "3.300"
    ],
    "artifacts": [
        {
            "url": "file://Image-Size-3.300.tar.gz",
            "hashes": {
                "sha1": "9f041858d9b8aa85e2fe87f15efac70c3da1a8af",
                "sha256": "53c9b1f86531cde060ee63709d1fda73cabc0cf2d581d29b22b014781b9f026b",
                "ssdeep": "6144:eMRPrU9f7pnDPseJmE4butefVIbs/9eWD:OFzObutefqbs1eM",
                "swhid": "swh:1:cnt:9f041858d9b8aa85e2fe87f15efac70c3da1a8af"
            },
            "swhid": "swh:1:dir:cade704198cf9c6c10448b7729a8a180442299e0"
        }
    ],
    "licenses": "Artistic 2.0, LGPLv2",
    "aliases": [],
    "references": "https://metacpan.org/release/Image-Size"
}