{
    "id": "OSSA-20250205-5183",
    "version": "1.0.0",
    "severity": "High",
    "description": "Find and use installed modules in a (sub)category",
    "title": "Advisory for perl-Module-Find",
    "package_name": "perl-Module-Find",
    "publisher": "Generated by OSSA Collector",
    "last_updated": "2025-02-05T04:03:26.543208",
    "approvals": [
        {
            "consumption": true,
            "externalization": true
        }
    ],
    "purls": [
        "pkg:rpm/amzn/perl-Module-Find@0.15"
    ],
    "regex": [
        "^pkg:rpm/amzn/perl-Module-Find.*"
    ],
    "affected_versions": [
        "*.*",
        "0.15"
    ],
    "artifacts": [
        {
            "url": "file://Module-Find-0.15.tar.gz",
            "hashes": {
                "sha1": "36d3cbfa55739e695f26b7c35089f1faeda87dc6",
                "sha256": "5c5482a7fe3e9e1035b36a984470b886f7af095eeeff63f5f19aec8cd2d8a85e",
                "ssdeep": "96:K3AcAtweLtFVtp0Lj1YtX/xD2IArBh+GH7iUkMUK5+49DYZ7ao7DoPmb5MHGBkE/:K3aq4FWpwt2bhRiUNUS+4KxamxdfuY",
                "swhid": "swh:1:cnt:36d3cbfa55739e695f26b7c35089f1faeda87dc6"
            },
            "swhid": "swh:1:dir:472be23cb206ee80fc67639d90426669d2b9f861"
        }
    ],
    "licenses": "Artistic, GPL+",
    "aliases": [],
    "references": "https://metacpan.org/release/Module-Find"
}