{
    "id": "OSSA-20250204-9995",
    "version": "1.0.0",
    "severity": "Informational",
    "description": "Mockito JUnit 5 support",
    "title": "Advisory for mockito-junit-jupiter",
    "package_name": "mockito-junit-jupiter",
    "publisher": "Generated by OSSA Collector",
    "last_updated": "2025-02-04T20:50:04.237660",
    "approvals": [
        {
            "consumption": true,
            "externalization": true
        }
    ],
    "purls": [
        "pkg:rpm/amzn/mockito-junit-jupiter@3.12.4"
    ],
    "regex": [
        "^pkg:rpm/amzn/mockito-junit-jupiter.*"
    ],
    "affected_versions": [
        "*.*",
        "3.12.4"
    ],
    "artifacts": [
        {
            "url": "file://mockito-3.12.4.tar.gz",
            "hashes": {
                "sha1": "99ba4412c6a6916494914fc9f9c8074a258f2d79",
                "sha256": "03add369c20b03cb1ded7e17010ad01774159126ce1ea937f5258a4dbe51d3de",
                "ssdeep": "24576:fm97eSzFfXoSjQrJtJo6SfI4a/HEv3kLRe15g6379GNX:fA77Ff4SkDSfI4QHRo1W6rgNX",
                "swhid": "swh:1:cnt:99ba4412c6a6916494914fc9f9c8074a258f2d79"
            },
            "swhid": "swh:1:dir:cf37054a7370668eabd208186bd6eebb547c98ee"
        }
    ],
    "licenses": "MIT",
    "aliases": [],
    "references": "https://site.mockito.org/"
}